odoo/addons/l10n_br_ie_search/README.rst
odoo/addons/l10n_br_ie_search/__init__.py
odoo/addons/l10n_br_ie_search/__manifest__.py
odoo/addons/l10n_br_ie_search/i18n/l10n_br_ie_search.pot
odoo/addons/l10n_br_ie_search/i18n/pt_BR.po
odoo/addons/l10n_br_ie_search/models/__init__.py
odoo/addons/l10n_br_ie_search/models/res_config_settings.py
odoo/addons/l10n_br_ie_search/models/sefaz_webservice.py
odoo/addons/l10n_br_ie_search/readme/CONFIGURE.md
odoo/addons/l10n_br_ie_search/readme/CONTRIBUTORS.md
odoo/addons/l10n_br_ie_search/readme/DESCRIPTION.md
odoo/addons/l10n_br_ie_search/readme/USAGE.md
odoo/addons/l10n_br_ie_search/static/icon.png
odoo/addons/l10n_br_ie_search/static/description/icon.png
odoo/addons/l10n_br_ie_search/static/description/index.html
odoo/addons/l10n_br_ie_search/tests/__init__.py
odoo/addons/l10n_br_ie_search/tests/test_sefaz.py
odoo/addons/l10n_br_ie_search/tests/test_sintegra.py
odoo/addons/l10n_br_ie_search/views/res_config_settings_view.xml
odoo/addons/l10n_br_ie_search/wizard/__init__.py
odoo/addons/l10n_br_ie_search/wizard/extend_partner_cnpj_search_wizard.py
odoo_addon_l10n_br_ie_search-17.0.1.1.0.dist-info/METADATA
odoo_addon_l10n_br_ie_search-17.0.1.1.0.dist-info/WHEEL
odoo_addon_l10n_br_ie_search-17.0.1.1.0.dist-info/top_level.txt
odoo_addon_l10n_br_ie_search-17.0.1.1.0.dist-info/RECORD
