Metadata-Version: 2.1
Name: odoo-addon-l10n_br_ie_search
Version: 17.0.1.1.0
Requires-Python: >=3.10
Requires-Dist: erpbrasil.assinatura
Requires-Dist: erpbrasil.base
Requires-Dist: erpbrasil.edoc
Requires-Dist: erpbrasil.transmissao
Requires-Dist: odoo-addon-l10n_br_cnpj_search>=17.0dev,<17.1dev
Requires-Dist: odoo-addon-l10n_br_nfe>=17.0dev,<17.1dev
Requires-Dist: odoo>=17.0a,<17.1dev
Summary: =?utf-8?q?Integra=C3=A7=C3=A3o_com_a_API_SintegraWS_e_SEFAZ?=
Home-page: https://github.com/OCA/l10n-brazil
License: AGPL-3
Author: KMEE,Odoo Community Association (OCA)
Author-email: support@odoo-community.org
Classifier: Programming Language :: Python
Classifier: Framework :: Odoo
Classifier: Framework :: Odoo :: 17.0
Classifier: License :: OSI Approved :: GNU Affero General Public License v3
